calculator_fchapuis/__init__.py
calculator_fchapuis/setup.py
calculator_fchapuis/calculator_pckg/__init__.py
calculator_fchapuis/calculator_pckg/calculator.py
calculator_fchapuis/tests/__init__.py
calculator_fchapuis/tests/requirements.txt
calculator_fchapuis/tests/test_calculator.py
calculator_fchapuis-1.0.1.dist-info/LICENSE
calculator_fchapuis-1.0.1.dist-info/WHEEL
calculator_fchapuis-1.0.1.dist-info/METADATA
calculator_fchapuis-1.0.1.dist-info/RECORD
