Metadata-Version: 2.1
Name: calculator_fchapuis
Version: 1.0.1
Summary: calculator_package
Author-email: Fabiano Chapuis <fabiano.chapuis@gmail.com>
Classifier: License :: OSI Approved :: MIT License
Project-URL: Home, https://github.com/TuringCollegeSubmissions/fchapu-DWWP.1.5.git
